nnspect/__init__.py
nnspect/cli/__init__.py
nnspect/cli/launch.py
nnspect/common/config.py
nnspect/common/constants.py
nnspect/common/exceptions.py
nnspect/common/structures.py
nnspect/features/interceptor.py
nnspect/features/patchers.py
nnspect/features/recorders.py
nnspect/features/schemas.py
nnspect/features/storage.py
nnspect/interpretation/attribution/grad_cam.py
nnspect/interpretation/attribution/integrated_grad.py
nnspect/interpretation/attribution/lime.py
nnspect/interpretation/attribution/shap.py
nnspect/interpretation/concept/examples.py
nnspect/interpretation/probes/approximation.py
nnspect/interpretation/probes/epistemic.py
nnspect/interpretation/sparsecoder/archetypal.py
nnspect/interpretation/sparsecoder/base.py
nnspect/interpretation/sparsecoder/batch_topk.py
nnspect/interpretation/sparsecoder/jump_relu.py
nnspect/interpretation/sparsecoder/matryoshka.py
nnspect/interpretation/sparsecoder/relu.py
nnspect/interpretation/sparsecoder/topk.py
nnspect/models/bert.py
nnspect/models/clip.py
nnspect/models/detr.py
nnspect/models/dino_detr.py
nnspect/models/faster_rcnn.py
nnspect/models/fcos.py
nnspect/models/flux.py
nnspect/models/gemma.py
nnspect/models/gpt2.py
nnspect/models/gptj.py
nnspect/models/grounding_dino.py
nnspect/models/llama.py
nnspect/models/mistral.py
nnspect/models/mixtral.py
nnspect/models/phi.py
nnspect/models/qwen.py
nnspect/models/sdxl.py
nnspect/models/stable_diffusion.py
nnspect/models/yolo.py
nnspect/native/data/loaders.cpp
nnspect/native/features/view.cpp
nnspect/native/models/sparsecoder.cpp
nnspect/pipelines/composer.py
nnspect/serve/__init__.py
nnspect/serve/server.py
nnspect-0.1.0.dist-info/METADATA
nnspect-0.1.0.dist-info/WHEEL
nnspect-0.1.0.dist-info/entry_points.txt
nnspect-0.1.0.dist-info/licenses/LICENSE
nnspect-0.1.0.dist-info/RECORD
