Metadata-Version: 2.4
Name: nnspect
Version: 0.1.0
Summary: A framework for Composite AI safety
Author-email: Harshal Nandigramwar <harshal.nandigramwar@gmail.com>
License-File: LICENSE
Requires-Python: >=3.11
